autoDownload/__init__.py
autoDownload/__main__.py
autoDownload/adapters.py
autoDownload/console.py
autoDownload/download.py
autoDownload/pools.py
autoDownload/progress.py
autoDownload/tempdir.py
autoDownload/tk.py
autoDownload/unit.py
autoDownload-0.1.2.dist-info/LICENSE
autoDownload-0.1.2.dist-info/METADATA
autoDownload-0.1.2.dist-info/WHEEL
autoDownload-0.1.2.dist-info/entry_points.txt
autoDownload-0.1.2.dist-info/top_level.txt
autoDownload-0.1.2.dist-info/RECORD
