Metadata-Version: 2.1
Name: autoDownload
Version: 0.1.2
Summary: A simple, efficient, general-purpose Python multithreaded download library
Home-page: https://github.com/auto-download/
Author: kuankuan
Author-email: 2163826131@qq.com
License: Mulan PSL v2
Keywords: requests,download,http,thread
Platform: windows
Platform: linux
Platform: macos
Classifier: Development Status :: 3 - Alpha
Classifier: Environment :: Console
Classifier: Intended Audience :: Developers
Classifier: Programming Language :: Python :: 3
Classifier: Programming Language :: Python :: 3.12
Classifier: Operating System :: MacOS
Classifier: Operating System :: POSIX :: Linux
Classifier: Operating System :: Microsoft :: Windows
Classifier: License :: OSI Approved :: Mulan Permissive Software License v2 (MulanPSL-2.0)
Classifier: Typing :: Typed
License-File: LICENSE
Requires-Dist: requests
Requires-Dist: rich
Requires-Dist: exceptiongroup
Requires-Dist: Deprecated
